rafetch/__init__.py
rafetch/rafetch.py
rafetch-1.0.8.dist-info/LICENSE
rafetch-1.0.8.dist-info/METADATA
rafetch-1.0.8.dist-info/WHEEL
rafetch-1.0.8.dist-info/entry_points.txt
rafetch-1.0.8.dist-info/top_level.txt
rafetch-1.0.8.dist-info/RECORD
